{"CapturedAt":"2013-10-14T20:04:46.77914Z","Posts":[{"Id":"post-898592","Title":"Threadless Gets Into The Greeting Card Game With Strategic Partnership And Investment In Open Me","Author":"Ryan Lawler","Url":"http://techcrunch.com/2013/10/14/threadless-open-me/","Shares":0,"Likes":0,"Comments":0},{"Id":"post-898468","Title":"The Boston Meetup + Pitch-Off Is In One Month, Apply Now To Be In The Pitch-Off","Author":"Jordan Crook","Url":"http://techcrunch.com/2013/10/14/the-boston-meetup-pitch-off-is-in-one-month-apply-now-to-be-in-the-pitch-off/","Shares":0,"Likes":0,"Comments":0},{"Id":"post-891263","Title":"Europe’s iversity Launches 1st MOOCs With 100k+ Students & Curriculum Of 24 Courses","Author":"Natasha Lomas","Url":"http://techcrunch.com/2013/10/14/iversity-initial-students/","Shares":0,"Likes":0,"Comments":0},{"Id":"post-898644","Title":"iTunes Radio Product Manager Gareth Paul Jones Joins Twitter To Work On Ad Partnerships","Author":"Anthony Ha","Url":"http://techcrunch.com/2013/10/14/gareth-paul-jones-joins-twitter/","Shares":0,"Likes":0,"Comments":0},{"Id":"post-898583","Title":"Twitter Plans To Use What You Follow And Tweet To Target MoPub Ads On Other Apps. Here’s How","Author":"Josh Constine","Url":"http://techcrunch.com/2013/10/14/monetizing-the-interest-graph/","Shares":0,"Likes":0,"Comments":0},{"Id":"post-898562","Title":"PayPal Expands “Real World” Presence Via Integration With iPad Point-of-Sale Maker Revel Systems","Author":"Sarah Perez","Url":"http://techcrunch.com/2013/10/14/paypal-expands-real-world-presence-via-partnership-with-ipad-point-of-sale-maker-revel-systems/","Shares":0,"Likes":0,"Comments":0},{"Id":"post-898498","Title":"Skimbox Goes Beyond Email Triage With A “Priority Inbox” App For Consumers & Enterprise","Author":"Sarah Perez","Url":"http://techcrunch.com/2013/10/14/skimbox-goes-beyond-email-triage-with-a-priority-inbox-app-for-consumers-enterprise/","Shares":0,"Likes":0,"Comments":0},{"Id":"post-898449","Title":"Cluster Brings Simple Group Photo-Sharing To Android","Author":"Sarah Perez","Url":"http://techcrunch.com/2013/10/14/cluster-brings-simple-social-photo-sharing-to-android/","Shares":0,"Likes":0,"Comments":0},{"Id":"post-898463","Title":"Unbundled Channels Coming To Canada, But Terrible Taste Could Make It A Disaster","Author":"Darrell Etherington","Url":"http://techcrunch.com/2013/10/14/unbundled-channels-coming-to-canada-but-terrible-taste-could-make-it-a-disaster/","Shares":0,"Likes":0,"Comments":0},{"Id":"post-898406","Title":"TRAFI Raises $500K In Seed Funding To Be The Go-To Transit App For Emerging Markets","Author":"Darrell Etherington","Url":"http://techcrunch.com/2013/10/14/trafi-raises-500k-in-seed-funding-to-be-the-go-to-transit-app-for-emerging-markets/","Shares":0,"Likes":0,"Comments":0},{"Id":"post-898447","Title":"Australian Startups Zookal And Flirtey To Begin Delivering Textbook Orders By Drone","Author":"Catherine Shu","Url":"http://techcrunch.com/2013/10/14/australian-startups-zookal-and-flirtey-to-begin-delivering-textbook-orders-by-drone/","Shares":0,"Likes":0,"Comments":0},{"Id":"post-898320","Title":"Sonos Introduces The Play:1, A Little $199 Speaker With Big Sound","Author":"Ryan Lawler","Url":"http://techcrunch.com/2013/10/14/sonos-play1/","Shares":0,"Likes":0,"Comments":0},{"Id":"post-898369","Title":"With An Eye To More Revenue, Foursquare Opens Its Ads Platform To All Small Businesses","Author":"Ingrid Lunden","Url":"http://techcrunch.com/2013/10/14/with-an-eye-to-more-revenue-foursquare-opens-its-ads-platform-to-all-small-businesses/","Shares":0,"Likes":0,"Comments":0},{"Id":"post-898277","Title":"Microsoft Announces Update 3 For Windows Phone 8 Coming This Year With Larger Screens, More Live Tiles","Author":"Alex Wilhelm","Url":"http://techcrunch.com/2013/10/14/microsoft-announces-update-3-for-windows-phone-8-with-larger-screens-more-live-tiles-coming-this-year/","Shares":0,"Likes":0,"Comments":0},{"Id":"post-898391","Title":"In Call For Startups To Build Apps For The Super Broadband Highway, BT And TechHub Launch Infinity Lab","Author":"Steve O'Hear","Url":"http://techcrunch.com/2013/10/14/infinity-lab/","Shares":0,"Likes":0,"Comments":0},{"Id":"post-898358","Title":"Nintendo 2DS Review: Back To Basics Proves Brilliant For Mobile Console Gaming","Author":"Darrell Etherington","Url":"http://techcrunch.com/2013/10/14/nintendo-2ds-review/","Shares":0,"Likes":0,"Comments":0},{"Id":"post-897263","Title":"Israeli Startup Maverick Wants To Be “WordPress Of Digital Marketing” To Help SMBs Compete With Major Brands","Author":"Steve O'Hear","Url":"http://techcrunch.com/2013/10/14/maverick/","Shares":0,"Likes":0,"Comments":0},{"Id":"post-898373","Title":"5.9-inch HTC One Max With Fingerprint Sensor Allows You To Launch Apps With A Touch","Author":"Darrell Etherington","Url":"http://techcrunch.com/2013/10/14/htc-one-max/","Shares":0,"Likes":0,"Comments":0},{"Id":"post-898337","Title":"Job Outsourcing Marketplace Freelancer.com Files For $14.2M IPO","Author":"Catherine Shu","Url":"http://techcrunch.com/2013/10/14/job-outsourcing-marketplace-freelancer-com-files-for-14-2m-ipo/","Shares":0,"Likes":0,"Comments":0},{"Id":"post-898321","Title":"LG May Fire Back At Samsung With Its Own Curvy Smartphone Next Month","Author":"Chris Velazco","Url":"http://techcrunch.com/2013/10/13/lg-may-fire-back-at-samsung-with-its-own-curvy-smartphone-next-month/","Shares":0,"Likes":0,"Comments":0},{"Id":"post-898319","Title":"Facebook Buys Mobile Data Analytics Company Onavo, Reportedly For Up To $200M… And (Finally?) Gets Its Office In Israel","Author":"Ingrid Lunden","Url":"http://techcrunch.com/2013/10/13/facebook-buys-mobile-analytics-company-onavo-and-finally-gets-its-office-in-israel/","Shares":0,"Likes":0,"Comments":0},{"Id":"post-886986","Title":"Atlassian Earned $150M In Revenues Last Year But Competition Intensifies With Collaboration Providers","Author":"Alex Williams","Url":"http://techcrunch.com/2013/10/13/atlassian-earned-150m-in-revenues-last-year-but-competition-intensifies-with-collaboration-providers/","Shares":0,"Likes":0,"Comments":0},{"Id":"post-898302","Title":"Netflix Reportedly In Negotiations With U.S. Cable TV Providers","Author":"Catherine Shu","Url":"http://techcrunch.com/2013/10/13/netflix-reportedly-in-negotiations-with-u-s-cable-tv-providers/","Shares":0,"Likes":0,"Comments":0},{"Id":"post-894206","Title":"Of Course Harvard’s Larry Summers Hates The Thiel Fellowship","Author":"Darrell Silver and Dan Friedman","Url":"http://techcrunch.com/2013/10/13/of-course-larry-summers-hates-the-thiel-fellowship/","Shares":0,"Likes":0,"Comments":0},{"Id":"post-898258","Title":"The End Of The Library","Author":"Mg Siegler","Url":"http://techcrunch.com/2013/10/13/the-end-of-the-library/","Shares":0,"Likes":0,"Comments":0},{"Id":"post-894183","Title":"Woojer Is A Wearable Audio Accessory For Bass Junkies Who Want To Feel The Noise","Author":"Natasha Lomas","Url":"http://techcrunch.com/2013/10/13/woojer/","Shares":0,"Likes":0,"Comments":0},{"Id":"post-898251","Title":"Magnify Is Buying Waywire To Build A Consumer-Facing Video Curation Powerhouse","Author":"Ryan Lawler","Url":"http://techcrunch.com/2013/10/13/magnify-waywire/","Shares":0,"Likes":0,"Comments":0},{"Id":"post-898244","Title":"Microsoft: Yeah, The Surface RT’s Name Confused Consumers","Author":"Alex Wilhelm","Url":"http://techcrunch.com/2013/10/13/microsoft-yeah-the-surface-rts-name-confused-consumers/","Shares":0,"Likes":0,"Comments":0},{"Id":"post-897308","Title":"What Games Are: The Nintendo Difference Still Exists","Author":"Tadhg Kelly","Url":"http://techcrunch.com/2013/10/13/what-games-are-the-nintendo-difference-still-exists/","Shares":0,"Likes":0,"Comments":0},{"Id":"post-897307","Title":"Xero Zeros In On Another $150M To Do Battle With Intuit In The World Of Online SMB Accounting Software","Author":"Ingrid Lunden","Url":"http://techcrunch.com/2013/10/13/xero-zeros-in-on-another-150m-to-do-battle-with-intuit-in-the-world-of-online-smb-accounting-software/","Shares":0,"Likes":0,"Comments":0}]}